D FlipFlop/Dataflow/dff.vhdl
library IEEE;
use IEEE.STD_LOGIC_1164.ALL;

entity dff is
    Port ( D : in STD_LOGIC;
           clk : in STD_LOGIC;
           Q : out STD_LOGIC;
           Q_bar : out STD_LOGIC);
end dff;

architecture behavior of dff is
   signal d1, s1, r1 : STD_LOGIC;
   begin
    s1 <= D nand clk;
    d1 <= D nand D;
    r1 <= d1 nand clk;
    Q <= s1 nand Q_bar;
    Q_bar <= r1 nand Q;
end behavior;

D FlipFlop/Dataflow/testbench.vhdl
library IEEE;
use IEEE.STD_LOGIC_1164.ALL;

entity testbench is
end testbench;

architecture Working of testbench is
component dff is port(
    D : in STD_LOGIC;
    clk : in STD_LOGIC;
    Q : out STD_LOGIC;
    Q_bar : out STD_LOGIC);
end component;

signal D, clk, Q, Q_bar: std_logic;
begin

uut: dff port map(
    D=>D,
    clk=>clk,
    Q=>Q,
    Q_bar=>Q_bar);

stim_proc: process
begin
    clk<='0' ; D<='0'; wait for 1 ns;
    clk<='1' ; D<='0'; wait for 1 ns;
    clk<='0' ; D<='0'; wait for 1 ns;
    clk<='1' ; D<='0'; wait for 1 ns;
    clk<='0' ; D<='0'; wait for 1 ns;
    clk<='1' ; D<='0'; wait for 1 ns;
    clk<='0' ; D<='1'; wait for 1 ns;
    clk<='1' ; D<='1'; wait for 1 ns;
    clk<='0' ; D<='1'; wait for 1 ns;
    clk<='1' ; D<='1'; wait for 1 ns;
    clk<='0' ; D<='1'; wait for 1 ns;
    clk<='1' ; D<='1'; wait for 1 ns;
    clk<='0' ; D<='1'; wait for 1 ns;
    clk<='1' ; D<='1'; wait for 1 ns;
    clk<='0' ; D<='1'; wait for 1 ns;
    clk<='1' ; D<='0'; wait for 1 ns;
    clk<='0' ; D<='0'; wait for 1 ns;
    clk<='1' ; D<='0'; wait for 1 ns;
    clk<='0' ; D<='1'; wait for 1 ns;
    clk<='1' ; D<='1'; wait for 1 ns;
    clk<='0' ; D<='1'; wait for 1 ns;
wait;
end process;
end Working;

D FlipFlop/Dataflow/output.vcd
$date
  Sun May 26 22:36:22 2024
$end
$version
  GHDL v0
$end
$timescale
  1 fs
$end
$scope module standard $end
$upscope $end
$scope module textio $end
$upscope $end
$scope module std_logic_1164 $end
$upscope $end
$scope module testbench $end
$var reg 1 ! d $end
$var reg 1 " clk $end
$var reg 1 # q $end
$var reg 1 $ q_bar $end
$scope module uut $end
$var reg 1 % d $end
$var reg 1 & clk $end
$var reg 1 ' q $end
$var reg 1 ( q_bar $end
$var reg 1 ) d1 $end
$var reg 1 * s1 $end
$var reg 1 + r1 $end
$upscope $end
$upscope $end
$enddefinitions $end
#0
0!
0"
U#
U$
0%
0&
U'
U(
1)
1*
1+
#1000000
1"
0#
1$
1&
0'
1(
0+
#2000000
0"
0&
1+
#3000000
1"
1&
0+
#4000000
0"
0&
1+
#5000000
1"
1&
0+
#6000000
1!
0"
1%
0&
0)
1+
#7000000
1"
1#
0$
1&
1'
0(
0*
#8000000
0"
0&
1*
#9000000
1"
1&
0*
#10000000
0"
0&
1*
#11000000
1"
1&
0*
#12000000
0"
0&
1*
#13000000
1"
1&
0*
#14000000
0"
0&
1*
#15000000
0!
1"
0#
1$
0%
1&
0'
1(
1)
0+
#16000000
0"
0&
1+
#17000000
1"
1&
0+
#18000000
1!
0"
1%
0&
0)
1+
#19000000
1"
1#
0$
1&
1'
0(
0*
#20000000
0"
0&
1*
